magu/__init__.py
magu/properties.py
magu/tests.py
magu/controllers/__init__.py
magu/controllers/controller.py
magu/core/__init__.py
magu/core/router.py
magu/core/server.py
magu/core/auth/auth.py
magu/database/__init__.py
magu/database/database.py
magu/dtos/__init__.py
magu/dtos/dto.py
magu/models/__init__.py
magu/models/model.py
magu/repositories/repository.py
magu/services/__init__.py
magu/services/handler.py
magu-rip/__init__.py
magu-rip/cli.py
magu_rip-0.0.5.dist-info/METADATA
magu_rip-0.0.5.dist-info/WHEEL
magu_rip-0.0.5.dist-info/top_level.txt
magu_rip-0.0.5.dist-info/RECORD
