Metadata-Version: 2.4
Name: magu-rip
Version: 0.0.5
Summary: Simple Web Framework.
Requires-Dist: cffi
Requires-Dist: cryptography
Requires-Dist: pycparser
Requires-Dist: PyJWT
Requires-Dist: build
Requires-Dist: colorama
Requires-Dist: mysql-connector-python
Requires-Dist: packaging
Requires-Dist: pyproject_hooks
